linear_rl/__init__.py
linear_rl/basis.py
linear_rl/fourier.py
linear_rl/tile_coding.py
linear_rl/true_online_sarsa.py
linear_rl/tyles3.py
linear_rl-0.1.dist-info/LICENSE
linear_rl-0.1.dist-info/METADATA
linear_rl-0.1.dist-info/WHEEL
linear_rl-0.1.dist-info/top_level.txt
linear_rl-0.1.dist-info/RECORD
